ghp_utils_test/__init__.py
ghp_utils_test/operacoes.py
ghp_utils_test/saudacoes.py
ghp_utils_test-0.2.dist-info/LICENSE
ghp_utils_test-0.2.dist-info/METADATA
ghp_utils_test-0.2.dist-info/WHEEL
ghp_utils_test-0.2.dist-info/top_level.txt
ghp_utils_test-0.2.dist-info/RECORD
